adam_core-0.5.2.dist-info/METADATA
adam_core-0.5.2.dist-info/WHEEL
adam_core-0.5.2.dist-info/entry_points.txt
adam_core-0.5.2.dist-info/licenses/LICENSE.md
adam_core/__init__.py
adam_core/_version.py
adam_core/constants.py
adam_core/coordinates/__init__.py
adam_core/coordinates/cartesian.py
adam_core/coordinates/cometary.py
adam_core/coordinates/covariances.py
adam_core/coordinates/jacobian.py
adam_core/coordinates/keplerian.py
adam_core/coordinates/origin.py
adam_core/coordinates/residuals.py
adam_core/coordinates/spherical.py
adam_core/coordinates/tests/__init__.py
adam_core/coordinates/tests/conftest.py
adam_core/coordinates/tests/test_benchmarks.py
adam_core/coordinates/tests/test_cartesian.py
adam_core/coordinates/tests/test_cartesian_units.py
adam_core/coordinates/tests/test_cometary.py
adam_core/coordinates/tests/test_covariances.py
adam_core/coordinates/tests/test_keplerian.py
adam_core/coordinates/tests/test_origin.py
adam_core/coordinates/tests/test_residuals.py
adam_core/coordinates/tests/test_spherical.py
adam_core/coordinates/tests/test_transforms_cometary.py
adam_core/coordinates/tests/test_transforms_keplerian.py
adam_core/coordinates/tests/test_transforms_rotation.py
adam_core/coordinates/tests/test_transforms_spherical.py
adam_core/coordinates/tests/test_transforms_spice.py
adam_core/coordinates/tests/test_transforms_translation.py
adam_core/coordinates/tests/test_units.py
adam_core/coordinates/transform.py
adam_core/coordinates/types.py
adam_core/coordinates/units.py
adam_core/coordinates/variants.py
adam_core/dynamics/__init__.py
adam_core/dynamics/__pycache__/aberrations.add_light_time-15.py310.1.nbc
adam_core/dynamics/__pycache__/aberrations.add_light_time-15.py310.nbi
adam_core/dynamics/__pycache__/aberrations.add_stellar_aberration-86.py310.1.nbc
adam_core/dynamics/__pycache__/aberrations.add_stellar_aberration-86.py310.nbi
adam_core/dynamics/__pycache__/chi.calc_chi-13.py310.1.nbc
adam_core/dynamics/__pycache__/chi.calc_chi-13.py310.nbi
adam_core/dynamics/__pycache__/lagrange.apply_lagrange_coefficients-92.py310.1.nbc
adam_core-0.5.2.dist-info/RECORD
