Metadata-Version: 2.1
Name: adam_core
Version: 0.5.2
Summary: Core libraries for the ADAM platform
Keywords: astronomy,orbital mechanics,propagation
Author-Email: Kathleen Kiker <kathleen@b612foundation.org>, Alec Koumjian <alec@b612foundation.org>, Joachim Moeyens <moeyensj@uw.edu>, Spencer Nelson <spencer@b612foundation.org>, Nate Tellis <nate@b612foundation.org>
License: The MIT License (MIT)
Classifier: Operating System :: OS Independent
Classifier: Development Status :: 4 - Beta
Classifier: Intended Audience :: Science/Research
Classifier: License :: OSI Approved :: MIT License
Classifier: Programming Language :: Python
Classifier: Programming Language :: Python :: 3
Classifier: Topic :: Scientific/Engineering :: Astronomy
Project-URL: Documentation, https://github.com/B612-Asteroid-Institute/adam_core#README.md
Project-URL: Issues, https://github.com/B612-Asteroid-Institute/adam_core/issues
Project-URL: Source, https://github.com/B612-Asteroid-Institute/adam_core
Requires-Python: <3.13,>=3.11
Requires-Dist: astropy
Requires-Dist: astroquery
Requires-Dist: healpy
Requires-Dist: jax<=0.4.38,>=0.4.23; platform_system == "Darwin" and platform_machine == "x86_64"
Requires-Dist: jax; platform_system != "Darwin" or platform_machine != "x86_64"
Requires-Dist: jaxlib<=0.4.38,>=0.4.23; platform_system == "Darwin" and platform_machine == "x86_64"
Requires-Dist: jaxlib; platform_system != "Darwin" or platform_machine != "x86_64"
Requires-Dist: numba
Requires-Dist: numpy>=2.0.0
Requires-Dist: pdm
Requires-Dist: pyarrow>=13.0.0
Requires-Dist: pandas
Requires-Dist: ray
Requires-Dist: requests
Requires-Dist: scipy
Requires-Dist: spiceypy
Requires-Dist: quivr>=0.7.5
Requires-Dist: mpc-obscodes
Requires-Dist: naif-de440
Requires-Dist: naif-leapseconds
Requires-Dist: naif-eop-high-prec
Requires-Dist: naif-eop-predict
Requires-Dist: naif-eop-historical
Requires-Dist: naif-earth-itrf93
Requires-Dist: timezonefinder
Provides-Extra: plots
Requires-Dist: geopandas>=1.0.1; extra == "plots"
Requires-Dist: plotly>=5.24.1; extra == "plots"
Requires-Dist: nbformat>=4.2.0; extra == "plots"
Requires-Dist: matplotlib>=3.10.1; extra == "plots"
Provides-Extra: oem
Requires-Dist: oem>=0.4.5; extra == "oem"
